devops_code_generator/__init__.py
devops_code_generator/code_repository.py
devops_code_generator/devops_code_generator.py
devops_code_generator/git_source_code_repository.py
devops_code_generator/repository.py
devops_code_generator/source_code_repository.py
devops_code_generator-2024.26.2.dist-info/LICENSE
devops_code_generator-2024.26.2.dist-info/METADATA
devops_code_generator-2024.26.2.dist-info/WHEEL
devops_code_generator-2024.26.2.dist-info/RECORD
