Metadata-Version: 2.1
Name: devops-code-generator
Version: 2024.26.2
Summary: Parent python package containing common python modules for all devops code generators like pipeline code generator, infrastructure code generator, database code generator, deployment code generator, container image code generator, container deployment code generator, etc.
Home-page: https://github.com/devops-code-generators/devops-code-generator
License: MIT
Keywords: devops,code-generator,devops-platform,langchain,genai
Author: Sagar Velankar
Author-email: sagar.velankar@gmail.com
Requires-Python: >=3.9,<4.0
Classifier: Development Status :: 1 - Planning
Classifier: Intended Audience :: Developers
Classifier: License :: OSI Approved :: MIT License
Classifier: Operating System :: OS Independent
Classifier: Programming Language :: Python :: 3
Classifier: Programming Language :: Python :: 3.9
Classifier: Programming Language :: Python :: 3.10
Classifier: Programming Language :: Python :: 3.11
Classifier: Programming Language :: Python :: 3.12
Classifier: Topic :: Software Development :: Code Generators
Requires-Dist: GitPython (>=3.1.43,<4.0.0)
Project-URL: Repository, https://github.com/devops-code-generators/devops-code-generator
